CHANGELOG.md
activity_tracking/__init__.py
activity_tracking/functions.py
activity_tracking-0.0.1.dist-info/LICENSE
activity_tracking-0.0.1.dist-info/WHEEL
activity_tracking-0.0.1.dist-info/METADATA
activity_tracking-0.0.1.dist-info/RECORD
