Metadata-Version: 2.1
Name: activity-tracking
Version: 0.0.1
Summary: Utility functions for desktop activity tracking
Home-page: https://github.com/elpachongco/activity-tracking-lib
License: BSD-3-Clause 
Keywords: desktop
Author: elpachongco
Author-email: earlsiachongco@gmail.com
Requires-Python: >=3.8,<4.0
Classifier: License :: Other/Proprietary License
Classifier: Programming Language :: Python :: 3
Classifier: Programming Language :: Python :: 3.10
Classifier: Programming Language :: Python :: 3.8
Classifier: Programming Language :: Python :: 3.9
Project-URL: Repository, https://github.com/elpachongco/activity-tracking-lib
